{"lastUsed":1667151064674,"path":"D:\/Eclipse\/WorkSpace","projectCount":1,"recentFiles":[{"path":"\/FatecGame2D\/src\/entidade","parentWorkspace":"D:\/Eclipse\/WorkSpace","name":"Enpc.java","lastModified":1666470572973,"locationURI":"file:\/D:\/Eclipse\/WorkSpace\/FatecGame2D\/src\/entidade\/Enpc.java"},{"path":"\/FatecGame2D\/src\/objetos","parentWorkspace":"D:\/Eclipse\/WorkSpace","name":"Moeda.java","lastModified":1667150724518,"locationURI":"file:\/D:\/Eclipse\/WorkSpace\/FatecGame2D\/src\/objetos\/Moeda.java"},{"path":"\/FatecGame2D\/src\/main","parentWorkspace":"D:\/Eclipse\/WorkSpace","name":"setAssets.java","lastModified":1667150724517,"locationURI":"file:\/D:\/Eclipse\/WorkSpace\/FatecGame2D\/src\/main\/setAssets.java"},{"path":"\/FatecGame2D\/src\/main","parentWorkspace":"D:\/Eclipse\/WorkSpace","name":"InputKeys.java","lastModified":1666966214861,"locationURI":"file:\/D:\/Eclipse\/WorkSpace\/FatecGame2D\/src\/main\/InputKeys.java"},{"path":"\/FatecGame2D\/src\/main","parentWorkspace":"D:\/Eclipse\/WorkSpace","name":"UI.java","lastModified":1667150724517,"locationURI":"file:\/D:\/Eclipse\/WorkSpace\/FatecGame2D\/src\/main\/UI.java"},{"path":"\/FatecGame2D\/src\/objetos","parentWorkspace":"D:\/Eclipse\/WorkSpace","name":"barraVida.java","lastModified":1667150724518,"locationURI":"file:\/D:\/Eclipse\/WorkSpace\/FatecGame2D\/src\/objetos\/barraVida.java"},{"path":"\/FatecGame2D\/src\/tile","parentWorkspace":"D:\/Eclipse\/WorkSpace","name":"Tile.java","lastModified":1666198513707,"locationURI":"file:\/D:\/Eclipse\/WorkSpace\/FatecGame2D\/src\/tile\/Tile.java"},{"path":"\/FatecGame2D\/res\/mapas","parentWorkspace":"D:\/Eclipse\/WorkSpace","name":"mapa1.txt","lastModified":1666648775337,"locationURI":"file:\/D:\/Eclipse\/WorkSpace\/FatecGame2D\/res\/mapas\/mapa1.txt"},{"path":"\/FatecGame2D\/src\/main","parentWorkspace":"D:\/Eclipse\/WorkSpace","name":"Main.java","lastModified":1667149307181,"locationURI":"file:\/D:\/Eclipse\/WorkSpace\/FatecGame2D\/src\/main\/Main.java"},{"path":"\/FatecGame2D\/src\/main","parentWorkspace":"D:\/Eclipse\/WorkSpace","name":"ChecarColisao.java","lastModified":1667150724517,"locationURI":"file:\/D:\/Eclipse\/WorkSpace\/FatecGame2D\/src\/main\/ChecarColisao.java"},{"path":"\/FatecGame2D\/src\/objetos","parentWorkspace":"D:\/Eclipse\/WorkSpace","name":"Livro.java","lastModified":1667150724517,"locationURI":"file:\/D:\/Eclipse\/WorkSpace\/FatecGame2D\/src\/objetos\/Livro.java"},{"path":"\/FatecGame2D\/src\/main","parentWorkspace":"D:\/Eclipse\/WorkSpace","name":"GamePainel.java","lastModified":1667150826052,"locationURI":"file:\/D:\/Eclipse\/WorkSpace\/FatecGame2D\/src\/main\/GamePainel.java"},{"path":"\/FatecGame2D\/src\/tile","parentWorkspace":"D:\/Eclipse\/WorkSpace","name":"TileManager.java","lastModified":1666198513642,"locationURI":"file:\/D:\/Eclipse\/WorkSpace\/FatecGame2D\/src\/tile\/TileManager.java"},{"path":"\/FatecGame2D\/src\/entidade","parentWorkspace":"D:\/Eclipse\/WorkSpace","name":"Entidade.java","lastModified":1667150265331,"locationURI":"file:\/D:\/Eclipse\/WorkSpace\/FatecGame2D\/src\/entidade\/Entidade.java"},{"path":"\/FatecGame2D\/src\/objetos","parentWorkspace":"D:\/Eclipse\/WorkSpace","name":"superObjetos.java","lastModified":1667150993759,"locationURI":"file:\/D:\/Eclipse\/WorkSpace\/FatecGame2D\/src\/objetos\/superObjetos.java"},{"path":"\/FatecGame2D\/src\/data","parentWorkspace":"D:\/Eclipse\/WorkSpace","name":"Conexao.java","lastModified":1667140995921,"locationURI":"file:\/D:\/Eclipse\/WorkSpace\/FatecGame2D\/src\/data\/Conexao.java"},{"path":"\/FatecGame2D\/src\/entidade","parentWorkspace":"D:\/Eclipse\/WorkSpace","name":"Player.java","lastModified":1667150422111,"locationURI":"file:\/D:\/Eclipse\/WorkSpace\/FatecGame2D\/src\/entidade\/Player.java"}]}